{
  "data": [
    {
      "duration": 0.195918367,
      "value": "Silence",
      "time": 0.0
    },
    {
      "duration": 21.596009069999997,
      "value": "no-function",
      "time": 0.195918367
    },
    {
      "duration": 19.098412699,
      "value": "no-function",
      "time": 21.791927437
    },
    {
      "duration": 14.808526077000003,
      "value": "no-function",
      "time": 40.890340136
    },
    {
      "duration": 6.373877551,
      "value": "no-function",
      "time": 55.698866213
    },
    {
      "duration": 19.945941042999998,
      "value": "no-function",
      "time": 62.072743764
    },
    {
      "duration": 19.853061224,
      "value": "no-function",
      "time": 82.018684807
    },
    {
      "duration": 34.94015872999999,
      "value": "no-function",
      "time": 101.871746031
    },
    {
      "duration": 13.752517006999994,
      "value": "no-function",
      "time": 136.811904761
    },
    {
      "duration": 19.024739229000005,
      "value": "no-function",
      "time": 150.564421768
    },
    {
      "duration": 6.440204082000008,
      "value": "no-function",
      "time": 169.589160997
    },
    {
      "duration": 13.515124716000003,
      "value": "no-function",
      "time": 176.029365079
    },
    {
      "duration": 10.566780045999991,
      "value": "Coda",
      "time": 189.544489795
    },
    {
      "duration": 3.547596372000015,
      "value": "Silence",
      "time": 200.111269841
    },
    {
      "duration": 0,
      "value": "End",
      "time": 203.658866213
    }
  ]
}