{
  "data": [
    {
      "duration": 0.034829931,
      "value": "Silence",
      "time": 0.0
    },
    {
      "duration": 50.674331066,
      "value": "Intro",
      "time": 0.034829931
    },
    {
      "duration": 32.082653061,
      "value": "Main-Theme",
      "time": 50.709160997
    },
    {
      "duration": 15.933106576,
      "value": "Interlude",
      "time": 82.791814058
    },
    {
      "duration": 33.869705216,
      "value": "Development",
      "time": 98.724920634
    },
    {
      "duration": 31.846190476000004,
      "value": "Interlude",
      "time": 132.59462585
    },
    {
      "duration": 29.333378684999985,
      "value": "Theme",
      "time": 164.440816326
    },
    {
      "duration": 6.389410431000016,
      "value": "Interlude",
      "time": 193.774195011
    },
    {
      "duration": 6.444557822999997,
      "value": "Solo",
      "time": 200.163605442
    },
    {
      "duration": 12.939773242000001,
      "value": "Transition",
      "time": 206.608163265
    },
    {
      "duration": 9.477641723999994,
      "value": "Interlude",
      "time": 219.547936507
    },
    {
      "duration": 13.514421768999995,
      "value": "Coda",
      "time": 229.025578231
    },
    {
      "duration": 12.240068027000007,
      "value": "no-function",
      "time": 242.54
    },
    {
      "duration": 0.6548979590000101,
      "value": "Silence",
      "time": 254.780068027
    },
    {
      "duration": 0,
      "value": "End",
      "time": 255.434965986
    }
  ]
}